prediction/__init__.py
prediction/bayesian_optimization.py
prediction/evaluate.py
prediction/evaluate_online_learning.py
prediction/main.py
prediction/nvrgrad.py
prediction/train.py
prediction/configs/README.md
prediction/configs/best_config.json
prediction/configs/default.json
prediction/configs/online_learning.json
prediction/configs/online/README.md
prediction/configs/online/default.json
prediction/tools/__init__.py
prediction/tools/commonroad_dataset.py
prediction/tools/eval_analysis.py
prediction/tools/grad_variance.py
prediction/tools/rename.py
prediction/trained_models/best_model.tar
prediction/trained_models/online_learning.tar
prediction/utils/__init__.py
prediction/utils/cuda.py
prediction/utils/dataset.py
prediction/utils/geometry.py
prediction/utils/model.py
prediction/utils/neural_network.py
prediction/utils/preprocessing.py
prediction/utils/visualization.py
wale_net-3.0.3.dist-info/LICENSE
wale_net-3.0.3.dist-info/METADATA
wale_net-3.0.3.dist-info/WHEEL
wale_net-3.0.3.dist-info/top_level.txt
wale_net-3.0.3.dist-info/RECORD
